waldur_site_agent/__init__.py
waldur_site_agent/main.py
waldur_site_agent/backend/__init__.py
waldur_site_agent/backend/backends.py
waldur_site_agent/backend/clients.py
waldur_site_agent/backend/exceptions.py
waldur_site_agent/backend/structures.py
waldur_site_agent/backend/utils.py
waldur_site_agent/common/__init__.py
waldur_site_agent/common/agent_identity_management.py
waldur_site_agent/common/plugin_schemas.py
waldur_site_agent/common/processors.py
waldur_site_agent/common/structures.py
waldur_site_agent/common/utils.py
waldur_site_agent/event_processing/__init__.py
waldur_site_agent/event_processing/event_subscription_manager.py
waldur_site_agent/event_processing/handlers.py
waldur_site_agent/event_processing/listener.py
waldur_site_agent/event_processing/main.py
waldur_site_agent/event_processing/structures.py
waldur_site_agent/event_processing/utils.py
waldur_site_agent/polling_processing/__init__.py
waldur_site_agent/polling_processing/agent_membership_sync.py
waldur_site_agent/polling_processing/agent_order_process.py
waldur_site_agent/polling_processing/agent_report.py
waldur_site_agent/testing/__init__.py
waldur_site_agent/testing/cli.py
waldur_site_agent/testing/mock_backend.py
waldur_site_agent/testing/order_test_harness.py
waldur_site_agent/testing/template_engine.py
waldur_site_agent/testing/templates/README.md
waldur_site_agent/testing/templates/create/basic.json
waldur_site_agent/testing/templates/create/slurm-full.json
waldur_site_agent/testing/templates/create/with-limits.json
waldur_site_agent/testing/templates/terminate/basic.json
waldur_site_agent/testing/templates/update/attributes-and-limits.json
waldur_site_agent/testing/templates/update/limits-only.json
waldur_site_agent-0.8.2.dist-info/METADATA
waldur_site_agent-0.8.2.dist-info/WHEEL
waldur_site_agent-0.8.2.dist-info/entry_points.txt
waldur_site_agent-0.8.2.dist-info/licenses/LICENCE.md
waldur_site_agent-0.8.2.dist-info/RECORD
