Metadata-Version: 2.4
Name: waldur-site-agent
Version: 0.8.2
Summary: Agent for integrating service provider's site with Waldur Mastermind.
Project-URL: Homepage, https://waldur.com
Project-URL: Documentation, https://docs.waldur.com
Author-email: OpenNode Team <info@opennodecloud.com>
License-Expression: MIT
License-File: LICENCE.md
Classifier: Intended Audience :: Developers
Classifier: License :: OSI Approved :: MIT License
Classifier: Operating System :: OS Independent
Requires-Python: <4.0,>=3.9
Requires-Dist: importlib-metadata>=8.7.0; python_full_version == '3.9.*'
Requires-Dist: mypy>=1.18.2
Requires-Dist: paho-mqtt==2.1.0
Requires-Dist: pydantic>=2.0.0
Requires-Dist: pyyaml==6.0.1
Requires-Dist: requests==2.32.3
Requires-Dist: sentry-sdk==2.3.1
Requires-Dist: stomp-py<9,>=8.2.0
Requires-Dist: types-pyyaml<7,>=6.0.12.20240311
Requires-Dist: waldur-api-client==7.9.6
